openbayes_serving/__init__.py
openbayes_serving/cli.py
openbayes_serving/common.py
openbayes_serving/debug/__init__.py
openbayes_serving/debug/console.py
openbayes_serving/debug/static/app.css
openbayes_serving/debug/static/app.js
openbayes_serving/debug/static/highlight.pack.js
openbayes_serving/debug/static/index.html
openbayes_serving/debug/static/openbayes-randomized.css
openbayes_serving/debug/static/root-variables.css
openbayes_serving/debug/tbtools.py
openbayes_serving/event.py
openbayes_serving/parts/__init__.py
openbayes_serving/parts/onnx.py
openbayes_serving/parts/request.py
openbayes_serving/predictor-template.py
openbayes_serving/predictor.py
openbayes_serving/serv.py
openbayes_serving/utils/__init__.py
openbayes_serving/utils/check.py
openbayes_serving/utils/escapes.py
openbayes_serving/utils/log.py
openbayes_serving/utils/wsgi.py
openbayes_serving-0.5.0.dist-info/METADATA
openbayes_serving-0.5.0.dist-info/WHEEL
openbayes_serving-0.5.0.dist-info/entry_points.txt
openbayes_serving-0.5.0.dist-info/RECORD
